pydcmtk/__init__.py
pydcmtk/cda2dcm.py
pydcmtk/core.py
pydcmtk/dcm2json.py
pydcmtk/dcm2pdf.py
pydcmtk/dcm2pnm.py
pydcmtk/dcm2xml.py
pydcmtk/dcmcjpeg.py
pydcmtk/dcmcjpls.py
pydcmtk/dcmconv.py
pydcmtk/dcmcrle.py
pydcmtk/dcmdjpeg.py
pydcmtk/dcmdjpls.py
pydcmtk/dcmdrle.py
pydcmtk/dcmdspfn.py
pydcmtk/dcmdump.py
pydcmtk/dcmftest.py
pydcmtk/dcmgpdir.py
pydcmtk/dcmicmp.py
pydcmtk/dcmj2pnm.py
pydcmtk/dcml2pnm.py
pydcmtk/dcmmkcrv.py
pydcmtk/dcmmkdir.py
pydcmtk/dcmmklut.py
pydcmtk/dcmodify.py
pydcmtk/dcmp2pgm.py
pydcmtk/dcmprscp.py
pydcmtk/dcmprscu.py
pydcmtk/dcmpschk.py
pydcmtk/dcmpsmk.py
pydcmtk/dcmpsprt.py
pydcmtk/dcmpsrcv.py
pydcmtk/dcmpssnd.py
pydcmtk/dcmqridx.py
pydcmtk/dcmqrscp.py
pydcmtk/dcmqrti.py
pydcmtk/dcmquant.py
pydcmtk/dcmrecv.py
pydcmtk/dcmscale.py
pydcmtk/dcmsend.py
pydcmtk/dcmsign.py
pydcmtk/dcod2lum.py
pydcmtk/dconvlum.py
pydcmtk/drtdump.py
pydcmtk/dsr2html.py
pydcmtk/dsr2xml.py
pydcmtk/dsrdump.py
pydcmtk/dump2dcm.py
pydcmtk/echoscu.py
pydcmtk/findscu.py
pydcmtk/getscu.py
pydcmtk/img2dcm.py
pydcmtk/mkreport.py
pydcmtk/movescu.py
pydcmtk/msgserv.py
pydcmtk/pdf2dcm.py
pydcmtk/stl2dcm.py
pydcmtk/storescp.py
pydcmtk/storescu.py
pydcmtk/termscu.py
pydcmtk/wlmscpfs.py
pydcmtk/xml2dcm.py
pydcmtk/xml2dsr.py
pydcmtk-0.1.2a0.dist-info/LICENSE
pydcmtk-0.1.2a0.dist-info/METADATA
pydcmtk-0.1.2a0.dist-info/WHEEL
pydcmtk-0.1.2a0.dist-info/top_level.txt
pydcmtk-0.1.2a0.dist-info/RECORD
