Metadata-Version: 2.1
Name: pydcmtk
Version: 0.1.2a0
Author-email: lcscosta <lcscosta@disroot.org>
License: MIT License
Classifier: License :: OSI Approved :: MIT License
License-File: LICENSE
